hmclab/MassMatrices.py
hmclab/Optimizers.py
hmclab/Samplers.py
hmclab/Samples.py
hmclab/Visualization.py
hmclab/__init__.py
hmclab/_version.py
hmclab/Distributions/ElasticFullWaveform2D.py
hmclab/Distributions/LayeredRayTracing2D.py
hmclab/Distributions/LinearMatrix.py
hmclab/Distributions/SourceLocation.py
hmclab/Distributions/Transforms.py
hmclab/Distributions/__init__.py
hmclab/Distributions/base.py
hmclab/Helpers/AppendNPY.py
hmclab/Helpers/BetterABC.py
hmclab/Helpers/CaptureStdout.py
hmclab/Helpers/CustomExceptions.py
hmclab/Helpers/InterfaceMKL.py
hmclab/Helpers/Processing.py
hmclab/Helpers/RandomMatrices.py
hmclab/Helpers/Timers.py
hmclab/Helpers/__init__.py
notebooks/__init__.py
notebooks/tutorials/__init__.py
hmclab-1.0rc1.dist-info/LICENSE
hmclab-1.0rc1.dist-info/METADATA
hmclab-1.0rc1.dist-info/WHEEL
hmclab-1.0rc1.dist-info/top_level.txt
hmclab-1.0rc1.dist-info/RECORD
