Metadata-Version: 2.1
Name: hmclab
Version: 1.0rc1
Summary: A numerical laboratory for Bayesian Seismology
Home-page: https://github.com/larsgeb/hmclab
Author: Lars Gebraad, Andrea Zunino, Andreas Fichtner
Author-email: lars.gebraad@erdw.ethz.ch
Project-URL: Bug Tracker, https://github.com/larsgeb/hmclab/issues
Classifier: Development Status :: 5 - Production/Stable
Classifier: Programming Language :: Python :: 3.9
Classifier: License :: OSI Approved :: BSD License
Classifier: Operating System :: OS Independent
Requires-Python: >=3.9
License-File: LICENSE
Requires-Dist: dill (==0.3.5.1)
Requires-Dist: numpy
Requires-Dist: scipy
Requires-Dist: termcolor
Requires-Dist: matplotlib
Requires-Dist: tqdm
Requires-Dist: h5py
Requires-Dist: pyyaml
Requires-Dist: ipywidgets
Requires-Dist: multiprocess
Requires-Dist: tilemapbase
Requires-Dist: pandas
Requires-Dist: obspy
Provides-Extra: dev
Requires-Dist: pytest ; extra == 'dev'
Requires-Dist: pytest-notebook ; extra == 'dev'
Requires-Dist: pytest-harvest ; extra == 'dev'
Requires-Dist: pytest-cov ; extra == 'dev'
Requires-Dist: pytest-ordering ; extra == 'dev'
Requires-Dist: nbformat ; extra == 'dev'
Requires-Dist: black ; extra == 'dev'
Requires-Dist: autoclasstoc ; extra == 'dev'
Requires-Dist: codecov ; extra == 'dev'
Requires-Dist: flake8 ; extra == 'dev'
Requires-Dist: furo ; extra == 'dev'
Requires-Dist: ipywidgets ; extra == 'dev'
Requires-Dist: nbconvert ; extra == 'dev'
Requires-Dist: nbsphinx ; extra == 'dev'
Requires-Dist: numpydoc ; extra == 'dev'
Requires-Dist: pandoc ; extra == 'dev'
Requires-Dist: pre-commit ; extra == 'dev'
Requires-Dist: sphinx ; extra == 'dev'
Requires-Dist: sphinx-git ; extra == 'dev'
Requires-Dist: sphinxcontrib-bibtex ; extra == 'dev'
Requires-Dist: versioneer ; extra == 'dev'
Provides-Extra: testing
Requires-Dist: pytest ; extra == 'testing'
Requires-Dist: pytest-notebook ; extra == 'testing'
Requires-Dist: pytest-harvest ; extra == 'testing'
Requires-Dist: pytest-cov ; extra == 'testing'
Requires-Dist: pytest-ordering ; extra == 'testing'
Requires-Dist: nbformat ; extra == 'testing'
Requires-Dist: black ; extra == 'testing'
